awfl/auth.py
awfl/awfl_entry.py
awfl/commands.py
awfl/main.py
awfl/state.py
awfl/cmds/__init__.py
awfl/cmds/auth_cmds.py
awfl/cmds/common.py
awfl/cmds/config_cmds.py
awfl/cmds/deploy_cmds.py
awfl/cmds/dev_cmds.py
awfl/cmds/exec_ctl.py
awfl/cmds/model_cmds.py
awfl/cmds/router.py
awfl/cmds/workflows.py
awfl/cmds/dev/__init__.py
awfl/cmds/dev/commands.py
awfl/cmds/dev/core.py
awfl/cmds/dev/dev_config.py
awfl/cmds/dev/dev_state.py
awfl/cmds/dev/docker_utils.py
awfl/cmds/dev/ngrok_utils.py
awfl/cmds/dev/paths.py
awfl/cmds/dev/prompt_utils.py
awfl/cmds/dev/watcher.py
awfl/cmds/dev/yaml_ops.py
awfl/cmds/dev/subcommands/__init__.py
awfl/cmds/dev/subcommands/deploy.py
awfl/cmds/dev/subcommands/generate.py
awfl/cmds/dev/subcommands/logs.py
awfl/cmds/dev/subcommands/start.py
awfl/cmds/dev/subcommands/status.py
awfl/cmds/dev/subcommands/stop.py
awfl/consumer/__init__.py
awfl/consumer/cursors.py
awfl/consumer/debug.py
awfl/consumer/leader_lock.py
awfl/consumer/routing.py
awfl/consumer/sse_consumer.py
awfl/consumer/sse_parser.py
awfl/events/__init__.py
awfl/events/workspace.py
awfl/response_handler/__init__.py
awfl/response_handler/callbacks.py
awfl/response_handler/event_logger.py
awfl/response_handler/handler.py
awfl/response_handler/rh_utils.py
awfl/response_handler/session_state.py
awfl/response_handler/tests/test_sanitize.py
awfl/utils/__init__.py
awfl/utils/constants.py
awfl/utils/logging.py
awfl/utils/urls.py
awfl/utils/workflows.py
awfl-0.1.6.dist-info/licenses/LICENSE
awfl-0.1.6.dist-info/METADATA
awfl-0.1.6.dist-info/WHEEL
awfl-0.1.6.dist-info/entry_points.txt
awfl-0.1.6.dist-info/top_level.txt
awfl-0.1.6.dist-info/RECORD
