Metadata-Version: 2.4
Name: awfl
Version: 0.1.6
Summary: AWFL: AI Workflows CLI
Author: Paul Lorenz
License: MIT
Project-URL: Homepage, https://github.com/awfl-us/cli
Project-URL: Issues, https://github.com/awfl-us/cli/issues
Keywords: ai,workflows,cli,serverless,agents
Classifier: Development Status :: 4 - Beta
Classifier: Intended Audience :: Developers
Classifier: License :: OSI Approved :: Apache Software License
Classifier: Programming Language :: Python :: 3
Classifier: Programming Language :: Python :: 3 :: Only
Classifier: Programming Language :: Python :: 3.11
Classifier: Programming Language :: Python :: 3.12
Classifier: Programming Language :: Python :: 3.13
Classifier: Environment :: Console
Classifier: Operating System :: OS Independent
Requires-Python: >=3.11
License-File: LICENSE
Requires-Dist: prompt_toolkit
Requires-Dist: watchdog
Requires-Dist: aiohttp
Requires-Dist: pathspec
Requires-Dist: requests>=2.31
Requires-Dist: google-auth
Requires-Dist: packaging
Dynamic: license-file
